tradetime/__init__.py
tradetime/__version__.py
tradetime/data.csv
tradetime/tradetime.py
TradeTime-1.1.0.dist-info/LICENSE
TradeTime-1.1.0.dist-info/METADATA
TradeTime-1.1.0.dist-info/WHEEL
TradeTime-1.1.0.dist-info/top_level.txt
TradeTime-1.1.0.dist-info/RECORD
