Metadata-Version: 2.1
Name: TradeTime
Version: 1.1.0
Summary: Trade With TradeTime Like DateTime
Home-page: https://github.com/Sand-Quant/TradeTime
Author: SandQuant
Author-email: data@sandquant.com
License: UNKNOWN
Download-URL: https://pypi.org/project/TradeTime/
Keywords: Trade,Datetime
Platform: UNKNOWN
Classifier: Intended Audience :: Developers
Classifier: Natural Language :: Chinese (Simplified)
Classifier: Operating System :: OS Independent
Classifier: Programming Language :: Python :: 3.5
Classifier: Programming Language :: Python :: 3.6
Classifier: Programming Language :: Python :: 3.7
Classifier: Programming Language :: Python :: 3.8
Classifier: Programming Language :: Python :: 3.9
Requires-Python: >=3.5
Requires-Dist: pandas
Requires-Dist: sandinvest
